actipy/ActigraphReader.class
actipy/ActigraphReader.java
actipy/AxivityReader$BlockParser.class
actipy/AxivityReader.class
actipy/AxivityReader.java
actipy/GENEActivReader.class
actipy/GENEActivReader.java
actipy/NpyWriter.class
actipy/NpyWriter.java
actipy/__init__.py
actipy/_version.py
actipy/matrix_reader.py
actipy/processing.py
actipy/read_cwa.py
actipy/reader.py
actipy-3.8.0.dist-info/LICENSE.md
actipy-3.8.0.dist-info/METADATA
actipy-3.8.0.dist-info/WHEEL
actipy-3.8.0.dist-info/entry_points.txt
actipy-3.8.0.dist-info/top_level.txt
actipy-3.8.0.dist-info/RECORD
