Metadata-Version: 2.1
Name: actipy
Version: 3.8.0
Summary: Python package to process wearable accelerometer data
Home-page: https://github.com/OxWearables/actipy
Download-URL: https://github.com/OxWearables/actipy
Author: Shing Chan, Aiden Doherty
Maintainer: Shing Chan
Maintainer-email: shing.chan@ndph.ox.ac.uk
License: See LICENSE.md
Keywords: wearable accelerometer data processing
Classifier: Programming Language :: Python :: 3
Classifier: Topic :: Scientific/Engineering
Classifier: Topic :: Scientific/Engineering :: Bio-Informatics
Classifier: Topic :: Scientific/Engineering :: Information Analysis
Classifier: Topic :: Scientific/Engineering :: Medical Science Apps.
Requires-Python: >=3.8
License-File: LICENSE.md
Requires-Dist: numpy>=1.22
Requires-Dist: scipy>=1.7
Requires-Dist: pandas>=1.3
Requires-Dist: statsmodels>=0.13
Requires-Dist: tqdm
Provides-Extra: dev
Requires-Dist: flake8; extra == "dev"
Requires-Dist: autopep8; extra == "dev"
Requires-Dist: ipython; extra == "dev"
Requires-Dist: ipdb; extra == "dev"
Requires-Dist: twine; extra == "dev"
Requires-Dist: tomli; extra == "dev"
Requires-Dist: pytest; extra == "dev"
Requires-Dist: joblib; extra == "dev"
Requires-Dist: memray; extra == "dev"
Provides-Extra: docs
Requires-Dist: sphinx>=4.2; extra == "docs"
Requires-Dist: sphinx-rtd-theme>=1.0; extra == "docs"
Requires-Dist: readthedocs-sphinx-search>=0.1; extra == "docs"
Requires-Dist: docutils<0.18; extra == "docs"
